INSTALL.zsh
MANIFEST.in
README.txt
setup.py
MotifAnalysisPackage.egg-info/PKG-INFO
MotifAnalysisPackage.egg-info/SOURCES.txt
MotifAnalysisPackage.egg-info/dependency_links.txt
MotifAnalysisPackage.egg-info/entry_points.txt
MotifAnalysisPackage.egg-info/requires.txt
MotifAnalysisPackage.egg-info/top_level.txt
motifStatistics/__init__.py
motifStatistics/bedFunctions.py
motifStatistics/constants.py
motifStatistics/genome.py
motifStatistics/graphs.py
motifStatistics/html.py
motifStatistics/motif.py
motifStatistics/motifStatistics.py
motifStatistics/sort.py
motifStatistics/statistics.py
motifStatistics/util.py