Metadata-Version: 1.0
Name: MotifAnalysisPackage
Version: 0.0.1
Summary: Motif analysis package under construction
Home-page: UNKNOWN
Author: Eduardo G. Gusmao
Author-email: eduardo.gusmao@rwth-aachen.de
License: GPL
Keywords: tfbs
Platform: UNKNOWN
